CHANGELOG.md
README.md
agent_plugin_builder/__init__.py
agent_plugin_builder/__main__.py
agent_plugin_builder/agent_plugin_build_options.py
agent_plugin_builder/agent_plugin_builder.py
agent_plugin_builder/agent_plugin_builder_arguments.py
agent_plugin_builder/build_agent_plugin.py
agent_plugin_builder/platform_dependency_packaging_method.py
agent_plugin_builder/plugin_archive_generation.py
agent_plugin_builder/plugin_manifest.py
agent_plugin_builder/plugin_schema_generation.py
agent_plugin_builder/py.typed
agent_plugin_builder/setup_build_plugin_logging.py
agent_plugin_builder/vendor_dir_generation.py
agent_plugin_builder-0.6.0.dist-info/LICENSE
agent_plugin_builder-0.6.0.dist-info/METADATA
agent_plugin_builder-0.6.0.dist-info/WHEEL
agent_plugin_builder-0.6.0.dist-info/entry_points.txt
agent_plugin_builder-0.6.0.dist-info/RECORD
