Metadata-Version: 2.1
Name: agent-plugin-builder
Version: 0.6.0
Summary: Builder for Agent Plugins.
Home-page: https://github.com/guardicode/agent-plugin-builder
License: GPLv3
Author: Ilija Lazoroski
Author-email: ilija.lazoroski@gmail.com
Requires-Python: >=3.11,<4.0
Classifier: License :: OSI Approved :: GNU General Public License v3 (GPLv3)
Classifier: License :: Other/Proprietary License
Classifier: Programming Language :: Python :: 3
Classifier: Programming Language :: Python :: 3.11
Classifier: Programming Language :: Python :: 3.12
Requires-Dist: docker (>=7.1.0,<8.0.0)
Requires-Dist: monkey-types (>=1.0.0,<2.0.0)
Requires-Dist: pip (>=24.0,<25.0)
Requires-Dist: pyyaml (>=6.0.1,<7.0.0)
Project-URL: Repository, https://github.com/guardicode/agent-plugin-builder
